{"ARI": 0.708434414324722, "NMI": 0.6054452921710415, "JSD": 0.10776227989425782, "Precision": 0.9044561197175944, "Recall": 0.9035722209895718, "F1-Score": 0.9038527069189708, "ROC AUC": 0.9794543777454691, "Accuracy": 0.9035722209895718, "MEAPE-mu": 1.40543584888342, "MEAPE-std": 0.21244520397076677, "_runtime": 3391, "_timestamp": 1647989822, "_step": 3, "Plots: target vs predicted value of dd_fix_demo-gb_cls--shuffled:True--exclude at risk:00.6207852818959494": {"_type": "plotly-file", "path": "media/plotly/Plots: target vs predicted value of dd_fix_demo-gb_cls--shuffled:True--exclude at risk:00.6207852818959494_1_86bc9c81b6895655960f.plotly.json", "sha256": "86bc9c81b6895655960feebb783d7452375bafcc84241f81fe3e4d88942927c8", "size": 618862}, "Scatters: target vs predicted values of dd_fix_demo-gb_cls--shuffled:True--exclude at risk:0": {"_type": "plotly-file", "path": "media/plotly/Scatters: target vs predicted values of dd_fix_demo-gb_cls--shuffled:True--exclude at risk:0_2_c7c5fde6138137ace397.plotly.json", "sha256": "c7c5fde6138137ace397c588626b740b0f9a31aa44691caa2a3a1437c648626b", "size": 618215}, "Histograms: target vs predicted of dd_fix_demo-gb_cls--shuffled:True--exclude at risk:0": {"_type": "plotly-file", "path": "media/plotly/Histograms: target vs predicted of dd_fix_demo-gb_cls--shuffled:True--exclude at risk:0_3_dc31fa5c82f247f58e61.plotly.json", "sha256": "dc31fa5c82f247f58e615eb306a0376c1adc87b9d900bb2a6a20c774b6cec9ed", "size": 8995}, "_wandb": {"runtime": 3391}}