{"ARI": 0.10030816499275846, "NMI": 0.038028826992487184, "JSD": 0.2006466707741401, "Precision": 0.7154643098019602, "Recall": 0.756506309148265, "F1-Score": 0.7042065789943346, "ROC AUC": 0.7480882186735454, "Accuracy": 0.756506309148265, "MEAPE-mu": 23.148038546910726, "MEAPE-std": 0.7658264586327377, "_runtime": 9, "_timestamp": 1646916856, "_step": 3, "Plots: target vs predicted value of dd_ia_phono-l_cls--shuffled:True--exclude at risk:True-0.3013741889160726": {"_type": "plotly-file", "path": "media/plotly/Plots: target vs predicted value of dd_ia_phono-l_cls--shuffled:True--exclude at risk:True-0.3013741889160726_1_5ec3cef09e9a36544eea.plotly.json", "sha256": "5ec3cef09e9a36544eeaaedc45186f3d6cf3248042994002e2dd10b8aa8857ca", "size": 139754}, "Scatters: target vs predicted values of dd_ia_phono-l_cls--shuffled:True--exclude at risk:True": {"_type": "plotly-file", "path": "media/plotly/Scatters: target vs predicted values of dd_ia_phono-l_cls--shuffled:True--exclude at risk:True_2_6a5d7dc9620c769c7372.plotly.json", "sha256": "6a5d7dc9620c769c7372dbddd5ae55597cc52913fc4b3e9d86344b7fb9f45922", "size": 139107}, "Histograms: target vs predicted of dd_ia_phono-l_cls--shuffled:True--exclude at risk:True": {"_type": "plotly-file", "path": "media/plotly/Histograms: target vs predicted of dd_ia_phono-l_cls--shuffled:True--exclude at risk:True_3_e388640466f953969169.plotly.json", "sha256": "e388640466f9539691691e45e3fdd494465cdb64ebb2b7bcf7c3755b1f9216c3", "size": 8996}, "_wandb": {"runtime": 9}}