{"ARI": 0.11716922983436708, "NMI": 0.03468744412612592, "JSD": 0.21069725633670433, "Precision": 0.6385900037252018, "Recall": 0.5795516675779114, "F1-Score": 0.6042596359988198, "ROC AUC": 0.6767204948662049, "Accuracy": 0.5795516675779114, "MEAPE-mu": 2.7010977114247563, "MEAPE-std": 0.9280265000489778, "_runtime": 8, "_timestamp": 1646917652, "_step": 3, "Plots: target vs predicted value of dd_ia_phono-cnb_cls--shuffled:True--exclude at risk:0-0.45664872876499296": {"_type": "plotly-file", "path": "media/plotly/Plots: target vs predicted value of dd_ia_phono-cnb_cls--shuffled:True--exclude at risk:0-0.45664872876499296_1_cd4a5c4e124067caf279.plotly.json", "sha256": "cd4a5c4e124067caf27920ac0595a719f646b61cec8ca7c8fcc93cf4f4d27117", "size": 150541}, "Scatters: target vs predicted values of dd_ia_phono-cnb_cls--shuffled:True--exclude at risk:0": {"_type": "plotly-file", "path": "media/plotly/Scatters: target vs predicted values of dd_ia_phono-cnb_cls--shuffled:True--exclude at risk:0_2_d3134d605882c62c45ab.plotly.json", "sha256": "d3134d605882c62c45ab447018ac12947b67d110cbf028d83d837433b21cb619", "size": 149896}, "Histograms: target vs predicted of dd_ia_phono-cnb_cls--shuffled:True--exclude at risk:0": {"_type": "plotly-file", "path": "media/plotly/Histograms: target vs predicted of dd_ia_phono-cnb_cls--shuffled:True--exclude at risk:0_3_e197f9c7e8b89cbd99e5.plotly.json", "sha256": "e197f9c7e8b89cbd99e58a66813216ca57fee4185f5c61c48e7ee2e6eddbea71", "size": 8994}, "_wandb": {"runtime": 8}}