{"ARI": 0.12303376079856224, "NMI": 0.0680780763841148, "JSD": 0.18854786108850766, "Precision": 0.6580356536866854, "Recall": 0.7257709251101322, "F1-Score": 0.6615383289708053, "ROC AUC": 0.7224021103652937, "Accuracy": 0.7257709251101322, "MEAPE-mu": 23.1496280855127, "MEAPE-std": 1.6120203006664313, "_runtime": 4, "_timestamp": 1654268729, "_step": 3, "Plots: target vs predicted value of dd_fix_stats-l_cls--shuffled:True--exclude at risk:0--pp: mm-spec-0.24637740989968204": {"_type": "plotly-file", "path": "media/plotly/Plots: target vs predicted value of dd_fix_stats-l_cls--shuffled:True--exclude at risk:0--pp: mm-spec-0.24637740989968204_1_f9fd60a5a514ab6293f2.plotly.json", "sha256": "f9fd60a5a514ab6293f2acd8a49477179c190e020aaaeb8b9b4ff31b2b023b73", "size": 31679}, "Scatters: target vs predicted values of dd_fix_stats-l_cls--shuffled:True--exclude at risk:0--pp: mm-spec": {"_type": "plotly-file", "path": "media/plotly/Scatters: target vs predicted values of dd_fix_stats-l_cls--shuffled:True--exclude at risk:0--pp: mm-spec_2_cfe9c9e6cc4266f85f86.plotly.json", "sha256": "cfe9c9e6cc4266f85f86618dcce7e4284d26bb879bbe9c109adf192311795e9a", "size": 31038}, "Histograms: target vs predicted of dd_fix_stats-l_cls--shuffled:True--exclude at risk:0--pp: mm-spec": {"_type": "plotly-file", "path": "media/plotly/Histograms: target vs predicted of dd_fix_stats-l_cls--shuffled:True--exclude at risk:0--pp: mm-spec_3_f18f5e6a7b6ab47e96bd.plotly.json", "sha256": "f18f5e6a7b6ab47e96bd66ac8bfa9a29a39aa100c705e97eb4f872267b28972f", "size": 9007}, "_wandb": {"runtime": 5}}