{"ARI": 0.09165866278237732, "NMI": 0.06349826401936177, "JSD": 0.19787621460021443, "Precision": 0.5737303850030951, "Recall": 0.6552917683603284, "F1-Score": 0.5833612368028362, "ROC AUC": 0.7057641294106838, "Accuracy": 0.6552917683603284, "MEAPE-mu": 24.349264116582553, "MEAPE-std": 0.37426302510427145, "_runtime": 5, "_timestamp": 1645787588, "_step": 3, "Plots: target vs predicted value of dd_fix_demo-mnb_cls--shuffled:True--exclude at risk:0-0.3591986142496193": {"_type": "plotly-file", "path": "media/plotly/Plots: target vs predicted value of dd_fix_demo-mnb_cls--shuffled:True--exclude at risk:0-0.3591986142496193_1_08010b7f07bc36ed569f.plotly.json", "sha256": "08010b7f07bc36ed569fd3e1e7b70cb001583b7a62d0b3374ad93897eb1bdb9b", "size": 618860}, "Scatters: target vs predicted values of dd_fix_demo-mnb_cls--shuffled:True--exclude at risk:0": {"_type": "plotly-file", "path": "media/plotly/Scatters: target vs predicted values of dd_fix_demo-mnb_cls--shuffled:True--exclude at risk:0_2_c4d26a55c31277edec64.plotly.json", "sha256": "c4d26a55c31277edec64675137c80d611073569270b64bfd991b8d96391dae06", "size": 618214}, "Histograms: target vs predicted of dd_fix_demo-mnb_cls--shuffled:True--exclude at risk:0": {"_type": "plotly-file", "path": "media/plotly/Histograms: target vs predicted of dd_fix_demo-mnb_cls--shuffled:True--exclude at risk:0_3_b351c6102273a15a0b0f.plotly.json", "sha256": "b351c6102273a15a0b0fdffe410726d7e0ca7a452883e4a3bc6ec505df0bd79d", "size": 8996}, "_wandb": {"runtime": 6}}