{"ARI": 0.0, "NMI": 0.0, "JSD": 0.1780825084701762, "Precision": 0.3832618155944979, "Recall": 0.6190814288883958, "F1-Score": 0.4734311798729381, "ROC AUC": 0.565315309224311, "Accuracy": 0.6190814288883958, "MEAPE-mu": 39.219432008223656, "MEAPE-std": 0.19598268857957107, "_runtime": 1940, "_timestamp": 1646029409, "_step": 3, "Plots: target vs predicted value of dd_fix-sv_cls--shuffled:True--exclude at risk:0-0.5500043549451057": {"_type": "plotly-file", "path": "media/plotly/Plots: target vs predicted value of dd_fix-sv_cls--shuffled:True--exclude at risk:0-0.5500043549451057_1_4627a9d1cb03676548ec.plotly.json", "sha256": "4627a9d1cb03676548ec73797a80b586cf11d1ad5b03993bb65e079f10659bae", "size": 618836}, "Scatters: target vs predicted values of dd_fix-sv_cls--shuffled:True--exclude at risk:0": {"_type": "plotly-file", "path": "media/plotly/Scatters: target vs predicted values of dd_fix-sv_cls--shuffled:True--exclude at risk:0_2_5c8437af6993db4b4f26.plotly.json", "sha256": "5c8437af6993db4b4f26909f1fa7156be44b139eace7fecb6defe886a65575a1", "size": 618209}, "Histograms: target vs predicted of dd_fix-sv_cls--shuffled:True--exclude at risk:0": {"_type": "plotly-file", "path": "media/plotly/Histograms: target vs predicted of dd_fix-sv_cls--shuffled:True--exclude at risk:0_3_4d11f0abc6586dd58587.plotly.json", "sha256": "4d11f0abc6586dd585870531bca3f2929a3c40d2efa0c6b0b47322666fb62827", "size": 8990}, "_wandb": {"runtime": 1935}}