{"MAE": 20.22057288994197, "RMSE": 24.90308308994191, "MRAE": 0.685251742332994, "JSD": 0.13176511348213255, "R^2-Score": 0.466990208264361, "MEAPE-mu": 6.1702588901174416, "MEAPE-std": 5.409487348274628, "_runtime": 5, "_timestamp": 1645482687, "_step": 3, "Plots: target vs predicted value of dd_demo-l_reg--shuffled:False--exclude at risk:True0.466990208264361": {"_type": "plotly-file", "path": "media/plotly/Plots: target vs predicted value of dd_demo-l_reg--shuffled:False--exclude at risk:True0.466990208264361_1_dfaa441b86dbf074eed2.plotly.json", "sha256": "dfaa441b86dbf074eed2fc39c3dfd62a0b8f4178f5f03c752ebb32680a7f3440", "size": 11155}, "Scatters: target vs predicted values of dd_demo-l_reg--shuffled:False--exclude at risk:True": {"_type": "plotly-file", "path": "media/plotly/Scatters: target vs predicted values of dd_demo-l_reg--shuffled:False--exclude at risk:True_2_891ba204616690bbd646.plotly.json", "sha256": "891ba204616690bbd64634d0ebc46548d74e61aefe1c4ee9316ea533a7037488", "size": 10537}, "Histograms: target vs predicted of dd_demo-l_reg--shuffled:False--exclude at risk:True": {"_type": "plotly-file", "path": "media/plotly/Histograms: target vs predicted of dd_demo-l_reg--shuffled:False--exclude at risk:True_3_16628568f2310e36e209.plotly.json", "sha256": "16628568f2310e36e209db1d46705b7cb456ee9b7d43ea3918ab760b98e9e984", "size": 8994}, "_wandb": {"runtime": 5}}