{"ARI": 0.05573298380992819, "NMI": 0.06017139748125441, "JSD": 0.21462019968943588, "Precision": 0.6650853889943074, "Recall": 0.6129032258064516, "F1-Score": 0.6170388751033912, "ROC AUC": 0.6334816462736373, "Accuracy": 0.6129032258064516, "MEAPE-mu": 25.411779988784122, "MEAPE-std": 13.930542022318026, "_runtime": 8, "_timestamp": 1645466111, "_step": 3, "Plots: target vs predicted value of dd_demo-gb_cls--shuffled:False--exclude at risk:0-0.9317507418397633": {"_type": "plotly-file", "path": "media/plotly/Plots: target vs predicted value of dd_demo-gb_cls--shuffled:False--exclude at risk:0-0.9317507418397633_1_9322c00b002b4e95a738.plotly.json", "sha256": "9322c00b002b4e95a738cd6f78b435d5c1a41edcfcc8bb81a743e333e022f6a2", "size": 10753}, "Scatters: target vs predicted values of dd_demo-gb_cls--shuffled:False--exclude at risk:0": {"_type": "plotly-file", "path": "media/plotly/Scatters: target vs predicted values of dd_demo-gb_cls--shuffled:False--exclude at risk:0_2_46607254751b60fe9bf6.plotly.json", "sha256": "46607254751b60fe9bf6600789498904d409d183e9b6898f052dd539fadee926", "size": 10108}, "Histograms: target vs predicted of dd_demo-gb_cls--shuffled:False--exclude at risk:0": {"_type": "plotly-file", "path": "media/plotly/Histograms: target vs predicted of dd_demo-gb_cls--shuffled:False--exclude at risk:0_3_faa3ce5e54ec46e8aa3f.plotly.json", "sha256": "faa3ce5e54ec46e8aa3f235e2cca7890bfcdbdb64d2700f420707a67a8c3d8f7", "size": 8988}, "_wandb": {"runtime": 10}}