{"MAE": 20.16041946131971, "MRAE": 0.38573400639495714, "R^2-Score": 0.4369899916056367, "MEAPE-mu": 5.870230908263798, "MEAPE-std": 4.3706286099545055, "RMSE": 25.754558132965066, "JSD": 0.12058913011455812, "_runtime": 3, "_timestamp": 1646479922, "_step": 3, "Plots: target vs predicted value of dd_demo-sv_reg--shuffled:False--exclude at risk:00.4369899916056367": {"_type": "plotly-file", "path": "media/plotly/Plots: target vs predicted value of dd_demo-sv_reg--shuffled:False--exclude at risk:00.4369899916056367_1_e39f1c1069750856fbfe.plotly.json", "sha256": "e39f1c1069750856fbfe7f74adbadd7650c1d8e79f5f9265fbeff2885896181a", "size": 11202}, "Scatters: target vs predicted values of dd_demo-sv_reg--shuffled:False--exclude at risk:0": {"_type": "plotly-file", "path": "media/plotly/Scatters: target vs predicted values of dd_demo-sv_reg--shuffled:False--exclude at risk:0_2_a9de5ded97e1ba4be73c.plotly.json", "sha256": "a9de5ded97e1ba4be73c7901e7b8f95dd187201857c1bc4dfb7976074dca0592", "size": 10584}, "Histograms: target vs predicted of dd_demo-sv_reg--shuffled:False--exclude at risk:0": {"_type": "plotly-file", "path": "media/plotly/Histograms: target vs predicted of dd_demo-sv_reg--shuffled:False--exclude at risk:0_3_0f7424d7452a35d4c87b.plotly.json", "sha256": "0f7424d7452a35d4c87bdef49b305e26318bfb85dec2fd7d86c13424147b5cfc", "size": 8992}, "_wandb": {"runtime": 3}}