{"MAE": 8.62668556056781, "MRAE": 0.17906726312031904, "R^2-Score": 0.8230019526284115, "MEAPE-mu": 0.10434977400382119, "MEAPE-std": 0.08023230511729158, "RMSE": 14.346304140072332, "JSD": Infinity, "_runtime": 13268, "_timestamp": 1650313236, "_step": 3, "Plots: target vs predicted value of dd_fix_demo-mlp_reg--shuffled:True--exclude at risk:00.8230019526284115": {"_type": "plotly-file", "path": "media/plotly/Plots: target vs predicted value of dd_fix_demo-mlp_reg--shuffled:True--exclude at risk:00.8230019526284115_1_418465e39ea208001490.plotly.json", "sha256": "418465e39ea2080014904df648ccd8c03f4ef598939fc388a2dd0507aa77d72f", "size": 966001}, "Scatters: target vs predicted values of dd_fix_demo-mlp_reg--shuffled:True--exclude at risk:0": {"_type": "plotly-file", "path": "media/plotly/Scatters: target vs predicted values of dd_fix_demo-mlp_reg--shuffled:True--exclude at risk:0_2_22f5bb6117306034b5f7.plotly.json", "sha256": "22f5bb6117306034b5f7990dc3e90f64ec0d0b6ac9b4f5c27c31a2633f7431fa", "size": 965384}, "Histograms: target vs predicted of dd_fix_demo-mlp_reg--shuffled:True--exclude at risk:0": {"_type": "plotly-file", "path": "media/plotly/Histograms: target vs predicted of dd_fix_demo-mlp_reg--shuffled:True--exclude at risk:0_3_d202c63fc328fe7f3a89.plotly.json", "sha256": "d202c63fc328fe7f3a89c2f5ac5fc34d8611b4bdab20ac512521132e90326f14", "size": 8999}, "_wandb": {"runtime": 13268}}