{"ARI": 0.44173482404141967, "NMI": 0.2644809338645202, "JSD": 0.15076459370419207, "Precision": 0.7676484338475923, "Recall": 0.7741935483870968, "F1-Score": 0.7697821891370279, "ROC AUC": 0.605773390186627, "Accuracy": 0.7741935483870968, "MEAPE-mu": 7.421956495003136, "MEAPE-std": 5.095998672154116, "_runtime": 16, "_timestamp": 1646944660, "_step": 3, "Plots: target vs predicted value of dd_phono-ab_cls--shuffled:True--exclude at risk:00.26409495548961437": {"_type": "plotly-file", "path": "media/plotly/Plots: target vs predicted value of dd_phono-ab_cls--shuffled:True--exclude at risk:00.26409495548961437_1_86fcf2e0ca160903230f.plotly.json", "sha256": "86fcf2e0ca160903230fec008808ce889d68104e64f280fa6cee714326daebdd", "size": 10753}, "Scatters: target vs predicted values of dd_phono-ab_cls--shuffled:True--exclude at risk:0": {"_type": "plotly-file", "path": "media/plotly/Scatters: target vs predicted values of dd_phono-ab_cls--shuffled:True--exclude at risk:0_2_7a9fbc953c7e9e36e797.plotly.json", "sha256": "7a9fbc953c7e9e36e797ede15197e8c30f38b0363de1597e8fdbdccc5079f3be", "size": 10107}, "Histograms: target vs predicted of dd_phono-ab_cls--shuffled:True--exclude at risk:0": {"_type": "plotly-file", "path": "media/plotly/Histograms: target vs predicted of dd_phono-ab_cls--shuffled:True--exclude at risk:0_3_02aa86cb4db56334ba5b.plotly.json", "sha256": "02aa86cb4db56334ba5b51dd496b4123248d9cc76c135f0e3c7c12508c640d28", "size": 8989}, "_wandb": {"runtime": 20}}