{"ARI": 0.10750488111626333, "NMI": 0.042656490577842814, "JSD": 0.21569971450144676, "Precision": 0.5408059908076552, "Recall": 0.6284446416685157, "F1-Score": 0.5752663688588152, "ROC AUC": 0.6748871601459521, "Accuracy": 0.6284446416685157, "MEAPE-mu": 13.76686085547152, "MEAPE-std": 0.38574716798923725, "_runtime": 49, "_timestamp": 1645793766, "_step": 3, "Plots: target vs predicted value of dd_fix_demo-l_cls--shuffled:False--exclude at risk:0-0.4901437304131888": {"_type": "plotly-file", "path": "media/plotly/Plots: target vs predicted value of dd_fix_demo-l_cls--shuffled:False--exclude at risk:0-0.4901437304131888_1_672fb057dbc1e5cc3363.plotly.json", "sha256": "672fb057dbc1e5cc3363f5009d467bfb6aade52adae0ee18a326feaee8e5eec2", "size": 618861}, "Scatters: target vs predicted values of dd_fix_demo-l_cls--shuffled:False--exclude at risk:0": {"_type": "plotly-file", "path": "media/plotly/Scatters: target vs predicted values of dd_fix_demo-l_cls--shuffled:False--exclude at risk:0_2_5c5fdea72f59134ccb0a.plotly.json", "sha256": "5c5fdea72f59134ccb0ad0216844cd0e3740ee54cbff585d04fd355f58116957", "size": 618215}, "Histograms: target vs predicted of dd_fix_demo-l_cls--shuffled:False--exclude at risk:0": {"_type": "plotly-file", "path": "media/plotly/Histograms: target vs predicted of dd_fix_demo-l_cls--shuffled:False--exclude at risk:0_3_9ec02d8c13a25f84f129.plotly.json", "sha256": "9ec02d8c13a25f84f129e940529e0b5a334b1d4de44b8b2482b75336d6265586", "size": 8994}, "_wandb": {"runtime": 49}}