{"ARI": 0.9873821260754417, "NMI": 0.9652834092253815, "JSD": 0.02283109344340827, "Precision": 0.9958227569649905, "Recall": 0.9958082741024239, "F1-Score": 0.9958066667700665, "ROC AUC": 0.9999211136535611, "Accuracy": 0.9958082741024239, "MEAPE-mu": 0.08720222942128147, "MEAPE-std": 0.07000580434645931, "_runtime": 128, "_timestamp": 1647393108, "_step": 3, "Plots: target vs predicted value of dd_ia_demo_phono-rf_cls--shuffled:True--exclude at risk:00.9825304914363281": {"_type": "plotly-file", "path": "media/plotly/Plots: target vs predicted value of dd_ia_demo_phono-rf_cls--shuffled:True--exclude at risk:00.9825304914363281_1_5823f291942e35310940.plotly.json", "sha256": "5823f291942e35310940c16c0a8615ebe0e4da02964aa22c7a674ef937cf0148", "size": 150547}, "Scatters: target vs predicted values of dd_ia_demo_phono-rf_cls--shuffled:True--exclude at risk:0": {"_type": "plotly-file", "path": "media/plotly/Scatters: target vs predicted values of dd_ia_demo_phono-rf_cls--shuffled:True--exclude at risk:0_2_84d0dc3063bfaebc55a2.plotly.json", "sha256": "84d0dc3063bfaebc55a2feeedabc52cd27c238586150b72d86bdc8377c8f02fb", "size": 149898}, "Histograms: target vs predicted of dd_ia_demo_phono-rf_cls--shuffled:True--exclude at risk:0": {"_type": "plotly-file", "path": "media/plotly/Histograms: target vs predicted of dd_ia_demo_phono-rf_cls--shuffled:True--exclude at risk:0_3_d8ec1587c7f7a40920bc.plotly.json", "sha256": "d8ec1587c7f7a40920bc3ce5e5cbd8d336084089d6fa42ba819567db4423ba8e", "size": 8999}, "_wandb": {"runtime": 130}}