{"MAE": 20.547456711447904, "RMSE": 23.91668016795489, "MRAE": 0.5209444782505439, "JSD": 0.11463561800885183, "R^2-Score": 0.6250046402510447, "MEAPE-mu": 3.615393853156178, "MEAPE-std": 2.4358701186277574, "_runtime": 4, "_timestamp": 1645389148, "_step": 3, "Plots: target vs predicted value of dd_demo-l_reg--shuffled:True--exclude at risk:True0.6250046402510447": {"_type": "plotly-file", "path": "media/plotly/Plots: target vs predicted value of dd_demo-l_reg--shuffled:True--exclude at risk:True0.6250046402510447_1_fb1d09e5c7645d538fd6.plotly.json", "sha256": "fb1d09e5c7645d538fd63ddfdd8d1cebcb831825c0570a9573f5c46b1ca9713e", "size": 11110}, "Scatters: target vs predicted values of dd_demo-l_reg--shuffled:True--exclude at risk:True": {"_type": "plotly-file", "path": "media/plotly/Scatters: target vs predicted values of dd_demo-l_reg--shuffled:True--exclude at risk:True_2_9c611b7225b174a1d38d.plotly.json", "sha256": "9c611b7225b174a1d38d863fc98230fbb9a7a035a06fcf1f2c4d41f02a8d056c", "size": 10483}, "Histograms: target vs predicted of dd_demo-l_reg--shuffled:True--exclude at risk:True": {"_type": "plotly-file", "path": "media/plotly/Histograms: target vs predicted of dd_demo-l_reg--shuffled:True--exclude at risk:True_3_769f37addefe768c0032.plotly.json", "sha256": "769f37addefe768c00327acf3e87f29ee873c348145d302aac6bcbb2cb15c9ab", "size": 8993}, "_wandb": {"runtime": 5}}