{"MAE": 19.54278723372967, "MRAE": 0.345721731579236, "R^2-Score": 0.5029321609515246, "MEAPE-mu": 0.3488380615925076, "MEAPE-std": 0.26625614871516395, "RMSE": 25.341000725664735, "JSD": Infinity, "_runtime": 6, "_timestamp": 1646484947, "_step": 3, "Plots: target vs predicted value of dd_ia_demo_phono-l_reg--shuffled:True--exclude at risk:True0.5029321609515246": {"_type": "plotly-file", "path": "media/plotly/Plots: target vs predicted value of dd_ia_demo_phono-l_reg--shuffled:True--exclude at risk:True0.5029321609515246_1_d4e860b8710a4397aa34.plotly.json", "sha256": "d4e860b8710a4397aa3463bbfee2da2de59d79ec8a5a90d8324d2fd50a099fa3", "size": 218302}, "Scatters: target vs predicted values of dd_ia_demo_phono-l_reg--shuffled:True--exclude at risk:True": {"_type": "plotly-file", "path": "media/plotly/Scatters: target vs predicted values of dd_ia_demo_phono-l_reg--shuffled:True--exclude at risk:True_2_e101a7912bc3da7ed1c6.plotly.json", "sha256": "e101a7912bc3da7ed1c65f65be418112ba85dc315d8687956140e4df9760fc5b", "size": 217684}, "Histograms: target vs predicted of dd_ia_demo_phono-l_reg--shuffled:True--exclude at risk:True": {"_type": "plotly-file", "path": "media/plotly/Histograms: target vs predicted of dd_ia_demo_phono-l_reg--shuffled:True--exclude at risk:True_3_cda7a357185de473a751.plotly.json", "sha256": "cda7a357185de473a751c38c3b0dbbcece5ba212ef3c651d93ad612abd4fc4ad", "size": 9004}, "_wandb": {"runtime": 6}}