{"ARI": 0.11732286393372524, "NMI": 0.03557345337100897, "JSD": 0.20575882266577175, "Precision": 0.6324549805128301, "Recall": 0.6769959897921983, "F1-Score": 0.6398699110961132, "ROC AUC": 0.6627699706182407, "Accuracy": 0.6769959897921983, "MEAPE-mu": 17.067283934592314, "MEAPE-std": 0.7363200338910149, "_runtime": 4, "_timestamp": 1645474779, "_step": 3, "Plots: target vs predicted value of dd_ia-gnb_cls--shuffled:True--exclude at risk:0-0.3740270356049835": {"_type": "plotly-file", "path": "media/plotly/Plots: target vs predicted value of dd_ia-gnb_cls--shuffled:True--exclude at risk:0-0.3740270356049835_1_3b5e883bd0145fbc8ccf.plotly.json", "sha256": "3b5e883bd0145fbc8ccf93752e60b0ff345b10826e82df6077566c732cb5acfa", "size": 150510}, "Scatters: target vs predicted values of dd_ia-gnb_cls--shuffled:True--exclude at risk:0": {"_type": "plotly-file", "path": "media/plotly/Scatters: target vs predicted values of dd_ia-gnb_cls--shuffled:True--exclude at risk:0_2_09184e8746a95f94e70c.plotly.json", "sha256": "09184e8746a95f94e70c70bfbe52d5cc9a6fac549273b30818f0e32ea7b6c5e7", "size": 149866}, "Histograms: target vs predicted of dd_ia-gnb_cls--shuffled:True--exclude at risk:0": {"_type": "plotly-file", "path": "media/plotly/Histograms: target vs predicted of dd_ia-gnb_cls--shuffled:True--exclude at risk:0_3_b9b79279ce8b2ccfb944.plotly.json", "sha256": "b9b79279ce8b2ccfb944ef7debc4265260085ca9a96a10bc4760092a691faf20", "size": 8989}, "_wandb": {"runtime": 4}}