{"ARI": 0.5104679802955665, "NMI": 0.3642944293477242, "JSD": 0.1579194797083614, "Precision": 0.8, "Recall": 0.8, "F1-Score": 0.8, "ROC AUC": 0.7828444904531862, "Accuracy": 0.8, "MEAPE-mu": 7.864279875445224, "MEAPE-std": 6.613407997877297, "_runtime": 9, "_timestamp": 1646947740, "_step": 3, "Plots: target vs predicted value of dd_phono-gb_cls--shuffled:True--exclude at risk:00.16149068322981364": {"_type": "plotly-file", "path": "media/plotly/Plots: target vs predicted value of dd_phono-gb_cls--shuffled:True--exclude at risk:00.16149068322981364_1_b90aa8178e65bc2dea7d.plotly.json", "sha256": "b90aa8178e65bc2dea7d8f62ce2802d65d9d8e9e60c77616efcd7a6d69461a13", "size": 10750}, "Scatters: target vs predicted values of dd_phono-gb_cls--shuffled:True--exclude at risk:0": {"_type": "plotly-file", "path": "media/plotly/Scatters: target vs predicted values of dd_phono-gb_cls--shuffled:True--exclude at risk:0_2_f014bc64e32ffcc2850e.plotly.json", "sha256": "f014bc64e32ffcc2850ef4a8ed070b3bc62dc777b03150678292e954386fc636", "size": 10100}, "Histograms: target vs predicted of dd_phono-gb_cls--shuffled:True--exclude at risk:0": {"_type": "plotly-file", "path": "media/plotly/Histograms: target vs predicted of dd_phono-gb_cls--shuffled:True--exclude at risk:0_3_b54e658fc1e394fe44b4.plotly.json", "sha256": "b54e658fc1e394fe44b43faf0ef4805f27b99651d40201271683d17ed702141d", "size": 8990}, "_wandb": {"runtime": 10}}